{"handle": "fisiomarcfornes", "layer": "adyacente", "verdict": "blend_feeder", "similarity": 55, "median": 10850.0, "n_videos": 80, "n_outliers": 15, "outliers": [{"id": "7510176145589931286", "views": 459800, "date": "2025-05-30", "desc": "🏃‍♂️ ¿Dolor inguinal o pubalgia relacionada con flexores de cadera? N...", "mult": 42.4, "url": "https://www.tiktok.com/@fisiomarcfornes/video/7510176145589931286", "type": "video"}, {"id": "7492009029116366102", "views": 338100, "date": "2025-04-11", "desc": "¿Te has torcido el tobillo? 🤕🦶 Una vez superada la fase aguda, ¡es mo...", "mult": 31.2, "url": "https://www.tiktok.com/@fisiomarcfornes/video/7492009029116366102", "type": "video"}, {"id": "7493110998258240790", "views": 249000, "date": "2025-04-14", "desc": "¿Dolor en la tibia al correr? 😫🏃🏻‍♂️ Podría ser periostitis tibial (s...", "mult": 22.9, "url": "https://www.tiktok.com/@fisiomarcfornes/video/7493110998258240790", "type": "video"}, {"id": "7510886969581391126", "views": 205800, "date": "2025-06-01", "desc": "Replying to @Fitness_style  🏃‍♂️ ¿Dolor lateral de rodilla al correr?...", "mult": 19.0, "url": "https://www.tiktok.com/@fisiomarcfornes/video/7510886969581391126", "type": "video"}, {"id": "7498676170028813590", "views": 164100, "date": "2025-04-29", "desc": "Ese dolor detrás de la rodilla… ¿te suena? 🦵🔥 El poplíteo puede estar...", "mult": 15.1, "url": "https://www.tiktok.com/@fisiomarcfornes/video/7498676170028813590", "type": "video"}, {"id": "7497193041120218390", "views": 94500, "date": "2025-04-25", "desc": "Dolor en la ingle entrenando? ⚽️⚠️ Podría ser una disfunción relacion...", "mult": 8.7, "url": "https://www.tiktok.com/@fisiomarcfornes/video/7497193041120218390", "type": "video"}, {"id": "7509067390622207254", "views": 85200, "date": "2025-05-27", "desc": "🍑 pov: tu fisio te enseña este ejercicio para el glúteo medio… …y de ...", "mult": 7.9, "url": "https://www.tiktok.com/@fisiomarcfornes/video/7509067390622207254", "type": "video"}, {"id": "7507196632224648470", "views": 83400, "date": "2025-05-22", "desc": "🦵 Copenhagen Plank: más que solo aductores 💥 Fortalecer la zona ingui...", "mult": 7.7, "url": "https://www.tiktok.com/@fisiomarcfornes/video/7507196632224648470", "type": "video"}, {"id": "7509800273548725526", "views": 81700, "date": "2025-05-29", "desc": "Replying to @lauradanielaperez42  🦵 ¿Quieres mejorar tu flexión de ro...", "mult": 7.5, "url": "https://www.tiktok.com/@fisiomarcfornes/video/7509800273548725526", "type": "video"}, {"id": "7492716975274085654", "views": 80500, "date": "2025-04-13", "desc": "¿Has visto este test antes? 🦵🤔 Apoyo sobre una pierna, giro controlad...", "mult": 7.4, "url": "https://www.tiktok.com/@fisiomarcfornes/video/7492716975274085654", "type": "video"}, {"id": "7500165405713960214", "views": 79700, "date": "2025-05-03", "desc": "¿Dolor en la planta del pie al dar los primeros pasos del día? 🦶🏼☀️ P...", "mult": 7.3, "url": "https://www.tiktok.com/@fisiomarcfornes/video/7500165405713960214", "type": "video"}, {"id": "7497560396048485654", "views": 73400, "date": "2025-04-26", "desc": "💥 ¿Dolor en la parte externa del codo? Podría ser epicondilitis o el ...", "mult": 6.8, "url": "https://www.tiktok.com/@fisiomarcfornes/video/7497560396048485654", "type": "video"}, {"id": "7512417941011418390", "views": 71700, "date": "2025-06-05", "desc": "🦵🔄 ¿Quieres mejorar la flexión de rodilla? La movilidad no se gana so...", "mult": 6.6, "url": "https://www.tiktok.com/@fisiomarcfornes/video/7512417941011418390", "type": "video"}, {"id": "7501259824760507670", "views": 56100, "date": "2025-05-06", "desc": "Replying to @Hugo Rolo  ¿Dolor en la parte interna del tobillo o tibi...", "mult": 5.2, "url": "https://www.tiktok.com/@fisiomarcfornes/video/7501259824760507670", "type": "video"}, {"id": "7508353526452571414", "views": 52000, "date": "2025-05-25", "desc": "🎾💢 ¿Dolor en el codo al agarrar, lanzar o golpear? Podría ser epicond...", "mult": 4.8, "url": "https://www.tiktok.com/@fisiomarcfornes/video/7508353526452571414", "type": "video"}]}